hlpl_arabic_words_synonym_antonym/__init__.py
hlpl_arabic_words_synonym_antonym/__main__.py
hlpl_arabic_words_synonym_antonym/arabic_words_synonym_antonym.py
hlpl_arabic_words_synonym_antonym/hlpl_arabic_words_synonym_antonym.db
hlpl_arabic_words_synonym_antonym/setup.cfg
hlpl_arabic_words_synonym_antonym-1.0.8.dist-info/LICENSE
hlpl_arabic_words_synonym_antonym-1.0.8.dist-info/METADATA
hlpl_arabic_words_synonym_antonym-1.0.8.dist-info/WHEEL
hlpl_arabic_words_synonym_antonym-1.0.8.dist-info/entry_points.txt
hlpl_arabic_words_synonym_antonym-1.0.8.dist-info/top_level.txt
hlpl_arabic_words_synonym_antonym-1.0.8.dist-info/RECORD
