Metadata-Version: 2.1
Name: hlpl-arabic-words-synonym-antonym
Version: 1.0.8
Summary: hlpl_arabic_words_synonym_antonym lists arabic words synonyms and antonyms in a readable database python package
Home-page: https://hlpl.net/resources
Download-URL: https://hlpl.net/resources/download/
Author: Ahmida Bendjoudi
Author-email: email@hlpl.net
License: MIT
Project-URL: hlpl, https://hlpl.net
Project-URL: hlpl_synonym_antonym-docs, https://docs.hlpl.net
Project-URL: hlpl_synonym_antonym-forum, https://hlpl.net/hlpl-forums
Project-URL: hlpl_synonym_antonym-github, https://github.com/hlpl/arabic-words-synonym-antonym
Keywords: hlpl_arabic_words_synonym_antonym,hlpl arabic words synonym antonym,arabic words synonym antonym,hlpl arabic words synonym antonym,hlpl,synonym antonym,words synonym antonym
Platform: UNKNOWN
Classifier: Natural Language :: Arabic
Requires-Python: >=3, <=3.9
License-File: LICENSE
